[
  {
    "name": "Geneva",
    "country": "Switzerland",
    "latitude": 46.20175590031008,
    "longitude": 6.1466014,
    "other_names": {
      "name": "Genève",
      "name:an": "Chinebra",
      "name:ar": "جنيف",
      "name:az": "Cenevrə",
      "name:be": "Жэнева",
      "name:bg": "Женева",
      "name:bo": "རི་ནོས་ཝ",
      "name:br": "Jeneva",
      "name:bs": "Ženeva",
      "name:ca": "Ginebra",
      "name:cs": "Ženeva",
      "name:cy": "Genefa",
      "name:da": "Geneve",
      "name:de": "Genf",
      "name:el": "Γενεύη",
      "name:en": "Geneva",
      "name:eo": "Ĝenevo",
      "name:es": "Ginebra",
      "name:et": "Genf",
      "name:eu": "Geneva",
      "name:fa": "ژنو",
      "name:fi": "Geneve",
      "name:fr": "Genève",
      "name:gl": "Xenebra",
      "name:he": "ז'נבה",
      "name:hr": "Ženeva",
      "name:hu": "Genf",
      "name:id": "Jenewa",
      "name:it": "Ginevra",
      "name:ja": "ジュネーヴ",
      "name:kn": "ಜೆನೇವ",
      "name:ku": "Cenevre",
      "name:lt": "Ženeva",
      "name:lv": "Ženēva",
      "name:nl": "Genève",
      "name:pl": "Genewa",
      "name:rm": "Genevra",
      "name:ru": "Женева",
      "name:sd": "جنيوا",
      "name:sk": "Ženeva",
      "name:sl": "Ženeva",
      "name:sr": "Женева",
      "name:th": "เจนีวา",
      "name:tr": "Cenevre",
      "name:tt": "Женева",
      "name:uk": "Женева",
      "name:ur": "جنیوا",
      "name:vi": "Giơ-ne-vơ",
      "name:zh": "日內瓦",
      "int_name": "Geneva",
      "name:azb": "ژنو",
      "name:gsw": "Genf",
      "name:pnb": "جنیوا",
      "alt_name:ku": "Jenev",
      "old_name:vi": "Nhật Nội Ngỏa",
      "name:kk-Arab": "جەنەۆا",
      "name:zh-Hans": "日内瓦",
      "name:zh-Hant": "日內瓦",
      "name:zh_pinyin": "Rìnèiwǎ"
    }
  },
  {
    "name": "Gengma",
    "country": "China",
    "latitude": 23.534813900359836,
    "longitude": 99.4003835,
    "other_names": {
      "name": "耿马县",
      "name:en": "Gengma",
      "name:ru": "Гэнсюань",
      "name:vi": "Cảnh Mã",
      "name:zh": "耿马县",
      "alt_name": "耿马;Gengma Dai and Va Autonomous County;Gengma County",
      "short_name": "耿马县",
      "name:zh-Hant": "耿馬縣",
      "official_name": "耿马傣族佤族自治县",
      "name:zh_pinyin": "Gěngmǎ xiàn"
    }
  },
  {
    "name": "Genhe",
    "country": "China",
    "latitude": 50.78116259928893,
    "longitude": 121.52516389999998,
    "other_names": {
      "name": "根河市",
      "name:en": "Genhe",
      "name:ja": "根河市",
      "name:mn": "Гэгээнгол",
      "name:ru": "Гэньхэ",
      "name:vi": "Căn Hà",
      "name:zh": "根河市",
      "alt_name": "根河;Gegen Yool;Гэгээнгол хот",
      "int_name": "Genhe",
      "name:zh-Hant": "根河市",
      "name:zh_pinyin": "Gēnhé Shì"
    }
  },
  {
    "name": "Genoa",
    "country": "Italy",
    "latitude": 44.40726000051392,
    "longitude": 8.9338624,
    "other_names": {
      "name": "Genova",
      "name:ar": "جنوة",
      "name:be": "Генуя",
      "name:ca": "Gènova",
      "name:cs": "Janov",
      "name:de": "Genua",
      "name:el": "Γένοβα",
      "name:en": "Genoa",
      "name:eo": "Ĝenovo",
      "name:es": "Génova",
      "name:fa": "جنوا",
      "name:fr": "Gênes",
      "name:gl": "Xénova",
      "name:hr": "Genova",
      "name:it": "Genova",
      "name:kn": "ಜೆನೋವ",
      "name:la": "Genua",
      "name:nl": "Genua",
      "name:oc": "Gènoa",
      "name:pl": "Genua",
      "name:pt": "Génova",
      "name:ru": "Генуя",
      "name:sk": "Janov",
      "name:sl": "Genova",
      "name:sv": "Genua",
      "name:uk": "Генуя",
      "name:zh": "热那亚",
      "name:ast": "Xénova",
      "name:lij": "Zena",
      "alt_name:gl": "Zena"
    }
  },
  {
    "name": "Geoje-si",
    "country": "South Korea",
    "latitude": 34.88046769964385,
    "longitude": 128.62120699999997,
    "other_names": {
      "name": "거제시",
      "name:de": "Geoje",
      "name:en": "Geoje-si",
      "name:es": "Geoje",
      "name:et": "Geoje",
      "name:fr": "Geoje",
      "name:ja": "巨済市",
      "name:ko": "거제시",
      "name:zh": "巨济市",
      "int_name": "Geoje",
      "name:ja_kana": "こじぇ",
      "name:ko-Hani": "巨濟市",
      "name:ko-Latn": "Geoje-si",
      "name:zh-Hant": "巨濟市"
    }
  },
  {
    "name": "George Town",
    "country": "Malaysia Singapore Brunei",
    "latitude": 5.414568099478577,
    "longitude": 100.3298035,
    "other_names": {
      "name": "George Town",
      "name:en": "George Town",
      "name:ja": "ジョージタウン",
      "name:ru": "Джорджтаун",
      "name:ta": "ஜோர்ஜ் டவுன்",
      "name:uk": "Джорджтаун",
      "name:zh": "乔治市",
      "alt_name:en": "Georgetown"
    }
  },
  {
    "name": "Geraldton",
    "country": "Australia",
    "latitude": -28.770349999357492,
    "longitude": 114.61471589999996,
    "other_names": {
      "name": "Geraldton",
      "name:en": "Geraldton",
      "name:ja": "ジェラルトン",
      "name:ru": "Джералдтон",
      "name:uk": "Джеральдтон"
    }
  },
  {
    "name": "Germa",
    "country": "Libya",
    "latitude": 26.528496900109147,
    "longitude": 13.069633799999998,
    "other_names": {
      "name": "مدينة جرمة",
      "name:ar": "مدينة جرمة",
      "name:de": "Garama",
      "name:en": "Germa",
      "name:es": "Germa",
      "name:fr": "Germa",
      "name:it": "Germa",
      "int_name": "Jarmah",
      "short_name:ar": "جرمة"
    }
  },
  {
    "name": "Gero",
    "country": "Japan",
    "latitude": 35.80642709971684,
    "longitude": 137.2433187,
    "other_names": {
      "name": "下呂市",
      "name:ar": "غيرو، غيفو",
      "name:de": "Gero",
      "name:en": "Gero",
      "name:es": "Gero",
      "name:fr": "Gero",
      "name:ja": "下呂市",
      "name:ko": "게로시",
      "name:pl": "Gero",
      "name:ru": "Геро",
      "name:uk": "Ґеро",
      "name:ja_rm": "Gero-shi",
      "name:ja_kana": "げろし"
    }
  },
  {
    "name": "Gêrzê",
    "country": "China",
    "latitude": 32.305100899598656,
    "longitude": 84.05991399999999,
    "other_names": {
      "name": "改则县",
      "name:bo": "སྒེར་རྩེ་རྫོང་།",
      "name:de": "Gêrzê",
      "name:en": "Gêrzê",
      "name:es": "Gêrzê",
      "name:fr": "Gêrzê",
      "name:vi": "Gêzêr",
      "name:zh": "改则县",
      "alt_name": "改则;Gerze;Gertse Dzong;Gaize;Gêrzê County",
      "name:zh-Hant": "改則縣",
      "name:zh_pinyin": "gǎizé xiàn"
    }
  },
  {
    "name": "Getafe",
    "country": "Spain",
    "latitude": 40.308180700308206,
    "longitude": -3.7302679,
    "other_names": {
      "name": "Getafe",
      "name:en": "Getafe",
      "name:hu": "Getafe",
      "name:ja": "ヘタフェ",
      "name:ru": "Хетафе",
      "name:zh": "赫塔费"
    }
  },
  {
    "name": "Gevgelija",
    "country": "Macedonia",
    "latitude": 41.13886640040736,
    "longitude": 22.503319199999996,
    "other_names": {
      "name": "Гевгелија",
      "name:de": "Gevgelija",
      "name:el": "Γευγελή",
      "name:en": "Gevgelija",
      "name:es": "Gevgelija",
      "name:et": "Gevgelija",
      "name:fr": "Guevgueliya",
      "name:mk": "Гевгелија",
      "name:pl": "Gewgelija",
      "name:ro": "Gevgelija",
      "name:ru": "Гевгелия",
      "name:sr": "Ђевђелија",
      "int_name": "Gevgelija"
    }
  },
  {
    "name": "Ghadames",
    "country": "Algeria",
    "latitude": 30.12584039972864,
    "longitude": 9.4900658,
    "other_names": {
      "name": "غدامس",
      "name:ar": "غدامس",
      "name:de": "Ghadames",
      "name:en": "Ghadames",
      "name:es": "Gadamés",
      "name:fr": "Ghadamès",
      "name:it": "Gadames",
      "name:ko": "가다메스",
      "name:ru": "Гадамес",
      "name:uk": "Гадамес",
      "alt_name": "Ghadamis",
      "int_name": "Ghadamis"
    }
  },
  {
    "name": "Ghadames",
    "country": "Libya",
    "latitude": 30.12584039972864,
    "longitude": 9.4900658,
    "other_names": {
      "name": "غدامس",
      "name:ar": "غدامس",
      "name:de": "Ghadames",
      "name:en": "Ghadames",
      "name:es": "Gadamés",
      "name:fr": "Ghadamès",
      "name:it": "Gadames",
      "name:ko": "가다메스",
      "name:ru": "Гадамес",
      "name:uk": "Гадамес",
      "alt_name": "Ghadamis",
      "int_name": "Ghadamis"
    }
  },
  {
    "name": "Ghanzi",
    "country": "Botswana",
    "latitude": -21.698968200231935,
    "longitude": 21.645240799999996,
    "other_names": {
      "name": "Ghanzi",
      "name:ar": "غانزي",
      "name:ko": "간지",
      "name:ru": "Ганзи",
      "name:uk": "Ґанзі"
    }
  },
  {
    "name": "Ghardaia",
    "country": "Algeria",
    "latitude": 32.4858549995942,
    "longitude": 3.677104,
    "other_names": {
      "name": "Ghardaïa ⵜⴰⵖⴻⵔⴷⴰⵢⵜ غرداية",
      "name:ar": "غرداية",
      "name:da": "Ghardaïa",
      "name:de": "Ghardaia",
      "name:el": "Γκαρντάια",
      "name:en": "Ghardaia",
      "name:es": "Gardaya",
      "name:eu": "Ghardaia",
      "name:fa": "غردایه",
      "name:fr": "Ghardaïa",
      "name:ja": "ガルダイア",
      "name:kk": "Гардая қаласы",
      "name:ko": "가르다이아",
      "name:ky": "Гардая",
      "name:pl": "Ghardaja",
      "name:pt": "Ghardaïa",
      "name:ru": "Гардая",
      "name:uk": "Гардая",
      "name:ur": "غرادیہ",
      "name:zh": "盖尔达耶",
      "alt_name": "Tagherdayt",
      "int_name": "Ghardaia",
      "name:azb": "غردایه",
      "name:ber": "ⵜⴰⵖⴻⵔⴷⴰⵢⵜ",
      "name:kab": "Taɣerdayt",
      "name:lzh": "盖尔达耶",
      "old_name": "Tagherdayt",
      "old_name:ar": "تغردايت"
    }
  },
  {
    "name": "Gharyan",
    "country": "Libya",
    "latitude": 32.171587299602635,
    "longitude": 13.021145099999998,
    "other_names": {
      "name": "غريان",
      "pcode": "LY-18-10520",
      "name:ar": "غريان",
      "name:de": "Garian",
      "name:en": "Gharyan",
      "name:es": "Garian",
      "name:et": "Gharyān",
      "name:fr": "Gharyan",
      "name:it": "Garian",
      "name:ber": "ⵖⵔⵢⴰⵏ"
    }
  },
  {
    "name": "Ghat",
    "country": "Libya",
    "latitude": 24.962629900261156,
    "longitude": 10.1797167,
    "other_names": {
      "name": "غات",
      "name:ar": "غات",
      "name:de": "Ghat",
      "name:en": "Ghat",
      "name:fr": "Ghat",
      "name:it": "Gat",
      "name:ko": "가트",
      "name:pl": "Ghat",
      "name:ru": "Гат"
    }
  },
  {
    "name": "Ghazali",
    "country": "Iraq",
    "latitude": 36.22115584387779,
    "longitude": 43.98857755517819,
    "other_names": {
      "name": "Ghazali"
    }
  },
  {
    "name": "Ghaziabad",
    "country": "India",
    "latitude": 28.67115269987239,
    "longitude": 77.41203559999998,
    "other_names": {
      "name": "Ghaziabad",
      "name:ar": "غازي آباد",
      "name:cs": "Ghaziabád",
      "name:de": "Ghaziabad",
      "name:en": "Ghaziabad",
      "name:es": "Ghaziabad",
      "name:fr": "Ghaziabad",
      "name:he": "גאזיאבאד",
      "name:hi": "ग़ाज़ियाबाद",
      "name:ja": "ガーズィヤーバード",
      "name:kn": "ಘಾಜಿಯಾಬಾದ್",
      "name:ko": "가지아바드",
      "name:ml": "ഗാസിയാബാദ്",
      "name:pa": "ਗ਼ਾਜ਼ੀਆਬਾਦ",
      "name:ru": "Газиабад",
      "name:ta": "காசியாபாத்",
      "name:uk": "Ґазіабад",
      "name:zh": "加兹阿巴德"
    }
  }
]